neural_commons/__init__.py
neural_commons/cf_nn/CFConv2d.py
neural_commons/cf_nn/CFLinear.py
neural_commons/cf_nn/CFModule.py
neural_commons/cf_nn/CFOptimizer.py
neural_commons/cf_nn/__init__.py
neural_commons/cf_nn/tests/__init__.py
neural_commons/cf_nn/tests/test_cf_optimizer.py
neural_commons/cf_nn/tests/utils.py
neural_commons/helpers/__init__.py
neural_commons/helpers/torch_helper.py
neural_commons/modules/AdaptiveSimpleNorm.py
neural_commons/modules/ArgMax.py
neural_commons/modules/ConvMixer2d.py
neural_commons/modules/GTanh.py
neural_commons/modules/GaELU.py
neural_commons/modules/GaussianNoise.py
neural_commons/modules/InputEncoder.py
neural_commons/modules/LogShape.py
neural_commons/modules/MAELoss.py
neural_commons/modules/NeuralLayer.py
neural_commons/modules/NeuralLayer2d.py
neural_commons/modules/ParametricReLU.py
neural_commons/modules/Permute.py
neural_commons/modules/Plus.py
neural_commons/modules/Quadratic.py
neural_commons/modules/RMSELoss.py
neural_commons/modules/RndNonLinearFunction.py
neural_commons/modules/RndProjection.py
neural_commons/modules/SMoE.py
neural_commons/modules/SMoEMixIn.py
neural_commons/modules/View.py
neural_commons/modules/__init__.py
neural_commons/opt/CosineScheduleOptimizer.py
neural_commons/opt/CosineScheduler.py
neural_commons/opt/TBCosineScheduleOptimizer.py
neural_commons/opt/__init__.py
neural_commons/q_nn/ParamModule.py
neural_commons/q_nn/QConv2d.py
neural_commons/q_nn/QGRFOptimizer.py
neural_commons/q_nn/QLinear.py
neural_commons/q_nn/__init__.py
neural_commons/q_nn/tests/__init__.py
neural_commons/q_nn/tests/test_qgrf_optimizer.py
neural_commons/q_nn/tests/utils.py
neural_commons-0.3.6.dist-info/METADATA
neural_commons-0.3.6.dist-info/WHEEL
neural_commons-0.3.6.dist-info/top_level.txt
neural_commons-0.3.6.dist-info/RECORD
